artificer/agents/__init__.py
artificer/agents/base.py
artificer/agents/debugger.py
artificer/agents/features.py
artificer/agents/registry.py
artificer_agents-0.1.0a22.dist-info/METADATA
artificer_agents-0.1.0a22.dist-info/WHEEL
artificer_agents-0.1.0a22.dist-info/licenses/LICENSE
artificer_agents-0.1.0a22.dist-info/RECORD
