Metadata-Version: 2.4
Name: artificer-agents
Version: 0.1.0a22
Summary: A library for creating agents
Author: Scott
License-Expression: MIT
License-File: LICENSE
Classifier: Development Status :: 3 - Alpha
Classifier: Intended Audience :: Developers
Classifier: License :: OSI Approved :: MIT License
Classifier: Programming Language :: Python :: 3
Classifier: Programming Language :: Python :: 3.13
Requires-Python: >=3.13
Requires-Dist: artificer-cli>=0.1.0a1
Requires-Dist: pydantic-ai>=0.1.0
Requires-Dist: questionary>=2.0
